spamclib/__init__.py
spamclib/async_tcp_client.py
spamclib/spamc_async_client.py
spamclib/spamc_body.py
spamclib/spamc_header.py
spamclib/spamc_protocol.py
spamclib/spamc_sync_client.py
spamclib/sync_tcp_client.py
spamclib/type_convert.py
spamclib-0.0.3.dist-info/LICENSE
spamclib-0.0.3.dist-info/METADATA
spamclib-0.0.3.dist-info/WHEEL
spamclib-0.0.3.dist-info/top_level.txt
spamclib-0.0.3.dist-info/RECORD
