Metadata-Version: 2.1
Name: spamclib
Version: 0.0.3
Summary: A SPAMC protocol library.Help you use SpamAssassin's SPAMD service.
Home-page: https://github.com/wevsty/spamclib
Author: wevsty
Author-email: ty@wevs.org
License: MIT
Keywords: spam spamc spamd spamassassin
Platform: UNKNOWN
Classifier: Development Status :: 3 - Alpha
Classifier: Programming Language :: Python :: 3.6
Classifier: Programming Language :: Python :: 3.7
Classifier: Intended Audience :: Developers
Classifier: Intended Audience :: System Administrators
Classifier: License :: OSI Approved :: MIT License
Classifier: Topic :: Communications :: Email :: Filters
Classifier: Topic :: Software Development :: Libraries
Requires-Python: >=3.6
